Metadata-Version: 1.0
Name: binogau-distributions
Version: 0.1
Summary: Gaussian distributions
Home-page: UNKNOWN
Author: Laxmi Priya Kasi
Author-email: UNKNOWN
License: UNKNOWN
Platform: UNKNOWN
